algorithm_question_fetcher/question_fetcher.py
algorithm_question_fetcher-1.0.0.dist-info/LICENSE.txt
algorithm_question_fetcher-1.0.0.dist-info/METADATA
algorithm_question_fetcher-1.0.0.dist-info/WHEEL
algorithm_question_fetcher-1.0.0.dist-info/entry_points.txt
algorithm_question_fetcher-1.0.0.dist-info/top_level.txt
algorithm_question_fetcher-1.0.0.dist-info/RECORD
