Metadata-Version: 2.1
Name: algorithm-question-fetcher
Version: 1.0.0
Summary: A python package that retrieves random number of algorithm questions specified by the user from toptal.com
Home-page: https://github.com/startng/forward-randalgo-babayega
Author: Kolapo Opeoluwa Olamidun
Author-email: kolapoolamidun@gmail.com
License: MIT
Platform: UNKNOWN
Classifier: License :: OSI Approved :: MIT License
Classifier: Programming Language :: Python :: 3
Classifier: Programming Language :: Python :: 3.7
Requires-Dist: beautifulsoup4
Requires-Dist: requests
